OMADS/Barrier.py
OMADS/Barriers.py
OMADS/CandidatePoint.py
OMADS/Directions.py
OMADS/Exploration.py
OMADS/Gmesh.py
OMADS/MADS.py
OMADS/Mesh.py
OMADS/Metrics.py
OMADS/Omesh.py
OMADS/Options.py
OMADS/POLL.py
OMADS/Parameters.py
OMADS/Point.py
OMADS/PreExploration.py
OMADS/PrePoll.py
OMADS/SEARCH.py
OMADS/__init__.py
OMADS/_common.py
OMADS/_globals.py
OMADS-2408.0.dist-info/LICENSE
OMADS-2408.0.dist-info/METADATA
OMADS-2408.0.dist-info/WHEEL
OMADS-2408.0.dist-info/top_level.txt
OMADS-2408.0.dist-info/RECORD
