Metadata-Version: 2.1
Name: OMADS
Version: 2408.0
Summary: Mesh Adaptive Direct Search (MADS)
Home-page: https://github.com/Ahmed-Bayoumy/OMADS
Author: Ahmed H. Bayoumy
Author-email: ahmed.bayoumy@mail.mcgill.ca
Project-URL: Bug Tracker, https://github.com/Ahmed-Bayoumy/OMADS/issues
Classifier: Programming Language :: Python :: 3
Classifier: Programming Language :: Python :: 3 :: Only
Classifier: Programming Language :: Python :: 3.8
Classifier: Programming Language :: Python :: 3.9
Classifier: Programming Language :: Python :: 3.11
Classifier: License :: OSI Approved :: GNU Lesser General Public License v3 (LGPLv3)
Classifier: Intended Audience :: Developers
Classifier: Operating System :: OS Independent
Requires-Python: >=3.8
License-File: LICENSE
Requires-Dist: pandas
Requires-Dist: setuptools >=58.1.0
Requires-Dist: scipy
Requires-Dist: pyDOE2
Requires-Dist: samplersLib >=2408
Provides-Extra: interactive
Requires-Dist: matplotlib >=3.5.2 ; extra == 'interactive'
Requires-Dist: plotly >=5.14.1 ; extra == 'interactive'
